libtetrabz/__init__.py
libtetrabz/libtetrabzc.cp39-win_amd64.pyd
libtetrabz-0.0.4.dist-info/LICENSE
libtetrabz-0.0.4.dist-info/METADATA
libtetrabz-0.0.4.dist-info/WHEEL
libtetrabz-0.0.4.dist-info/top_level.txt
libtetrabz-0.0.4.dist-info/RECORD
