Metadata-Version: 2.1
Name: libtetrabz
Version: 0.0.4
Summary: Optimized tetrahedron method to perform brillouin-zone integral
Home-page: https://libtetrabz.osdn.jp/
Author: Mitsuaki Kawamura
Author-email: kawamitsuaki@gmail.com
License: UNKNOWN
Project-URL: Bug Tracker, https://osdn.net/projects/libtetrabz/forums/
Platform: UNKNOWN
Classifier: Programming Language :: Python :: 3
Classifier: License :: OSI Approved :: MIT License
Classifier: Operating System :: OS Independent
Requires-Python: >=3.6
License-File: LICENSE
